yardstiq/__init__.py
yardstiq/versions.py
yardstiq/cli/__init__.py
yardstiq/cli/backend_cli.py
yardstiq/cli/benchmark_cli.py
yardstiq/cli/dataset_cli.py
yardstiq/cli/main_cli.py
yardstiq/cli/provider_cli.py
yardstiq/core/__init__.py
yardstiq/core/impl/__init__.py
yardstiq/core/impl/backend_impl.py
yardstiq/core/impl/benchmark_impl.py
yardstiq/core/impl/dataset_impl.py
yardstiq/core/impl/provider_impl.py
yardstiq/core/interfaces/__init__.py
yardstiq/core/interfaces/backend.py
yardstiq/core/interfaces/benchmark.py
yardstiq/core/interfaces/dataset.py
yardstiq/core/interfaces/provider.py
yardstiq/core/plugins/__init__.py
yardstiq/core/plugins/installed_plugins.py
yardstiq/core/plugins/local_manual_plugins.py
yardstiq/core/plugins/local_project_plugins.py
yardstiq/core/plugins/local_provider.py
yardstiq/data/known_providers.json
yardstiq/services/__init__.py
yardstiq/services/credentials.py
yardstiq-0.1.1.dist-info/licenses/LICENSE
yardstiq-0.1.1.dist-info/METADATA
yardstiq-0.1.1.dist-info/WHEEL
yardstiq-0.1.1.dist-info/entry_points.txt
yardstiq-0.1.1.dist-info/top_level.txt
yardstiq-0.1.1.dist-info/RECORD
